ssis_validator/__init__.py
ssis_validator/__main__.py
ssis_validator/ssis_validator.py
ssis_validator-0.1.2.dist-info/entry_points.txt
ssis_validator-0.1.2.dist-info/LICENSE
ssis_validator-0.1.2.dist-info/WHEEL
ssis_validator-0.1.2.dist-info/METADATA
ssis_validator-0.1.2.dist-info/RECORD
