Metadata-Version: 2.1
Name: ssis-validator
Version: 0.1.2
Summary: A Python package for validating SQL Server Integration Services (SSIS) packages
Home-page: https://github.com/mahdi-hosseini/ssis_validator
License: MIT
Author: Mike Hosseini
Author-email: mahdihosseini75@gmail.com
Requires-Python: >=3.7,<4.0
Classifier: License :: OSI Approved :: MIT License
Classifier: Programming Language :: Python :: 3
Classifier: Programming Language :: Python :: 3.7
Requires-Dist: colorama (>=0.4.1,<0.5.0)
Requires-Dist: crayons (>=0.2.0,<0.3.0)
Requires-Dist: gitpython (>=3.0,<4.0)
Requires-Dist: lxml (>=4.4,<5.0)
Project-URL: Repository, https://github.com/mahdi-hosseini/ssis_validator
